{
  "folder": {
    "questionnaires": [
      {
        "id": "",
        "name": "שברים שהמכנים שלהם שונים - 1"
      },
      {
        "id": "",
        "name": "שברים שהמכנים שלהם שונים - 2"
      },
      {
        "id": "",
        "name": "שברים שהמכנים שלהם שונים - 3"
      },
      {
        "id": "",
        "name": "שברים שהמכנים שלהם שונים - 4"
      },
      {
        "id": "",
        "name": "שברים שהמכנים שלהם שונים - 5"
      },
      {
        "id": "",
        "name": "שברים שהמכנים שלהם שונים - 6"
      },
      {
        "id": "",
        "name": "שברים שהמכנים שלהם שונים - 7"
      },
      {
        "id": "",
        "name": "שברים שהמכנים שלהם שונים - 8"
      },
      {
        "id": "",
        "name": "שברים שהמכנים שלהם שונים - 9"
      }

    ],
    "abilities": [

      {
        "questionnaire-order": 1,
        "value": 20,

        "students": [
          {
            "id": "",
            "name": "גורבט נעמי"
          }
        ]
      },
      {
        "questionnaire-order": 1,
        "value": 50,
        "students": [
          {
            "id": "",
            "name": "פורט ליאור"
          },
          {
            "id": "",
            "name": "נתניהו ביבי"
          }
        ]
      },
      {
        "questionnaire-order": 2,
        "value": 50,
        "finished": true,

        "students": [
          {
            "id": "",
            "name": "בלומנשטיק בן"
          },
          {
            "id": "",
            "name": "בן דנון שי שלמה"
          }
        ]
      },
      {
        "questionnaire-order": 3,
        "value": 90,
        "students": [
          {
            "id": "",
            "name": "בלאושטיין איריס",
            "finished": true
          },
          {
            "id": "",
            "name": "ביטון רומי"
          },
          {
            "id": "",
            "name": "בכר נטע"
          },
          {
            "id": "",
            "name": "ביילי תמרה"
          },
          {
            "id": "",
            "name": "אלכסנדר גיורא"
          }
        ]
      },
      {
        "questionnaire-order": 5,
        "value": 60,
        "finished": true,
        "students": [
          {
            "id": "",
            "name": "ניצן איל"
          },
          {
            "id": "",
            "name": "דליות רועי"
          },
          {
            "id": "",
            "name": "קיינן רונן"
          },
          {
            "id": "",
            "name": "ענברי ארבל אלון"
          },
          {
            "id": "",
            "name": "קרונפלד יובל"
          },
          {
            "id": "",
            "name": "רביבו אגם"
          }
        ]
      },
      {
        "questionnaire-order": 5,
        "value": 10,
        "students": [
          {
            "id": "",
            "name": "תלמיד 9"
          },
          {
            "id": "",
            "name": "תלמיד 10"
          }
        ]
      },
      {
        "questionnaire-order": 7,
        "value": 60,
        "students": [
          {
            "id": "",
            "name": "הרשקוביץ' שרה"
          },
          {
            "id": "",
            "name": "גוב גידי"
          },
          {
            "id": "",
            "name": "לידר עברי"
          },
          {
            "id": "",
            "name": "מאומן נ נח נחמן"
          },
          {
            "id": "",
            "name": "שורקמאיה"
          },
          {
            "id": "",
            "name": "ביטןדוד"
          },
          {
            "id": "",
            "name": "מילובביץ' הרב"
          },
          {
            "id": "",
            "name": "הראל אורן"
          },
          {
            "id": "",
            "name": "בן מוחה עדי תמר"
          },
          {
            "id": "",
            "name": "דולר לנדסמן אלמה"
          },
          {
            "id": "",
            "name": "ששון אגם מרסל"
          }
        ]
      },
      {
        "questionnaire-order": 9,
        "value": 30,
        "finished": true,
        "students": [
          {
            "id": "",
            "name": "תלמיד 6"
          },
          {
            "id": "",
            "name": "תלמיד 7"
          },
          {
            "id": "",
            "name": "תלמיד 8"
          },
          {
            "id": "",
            "name": "תלמיד 8"
          }
        ]
      }
    ],
    "folders": []
  }

} 